[
  {
    "nominal": "0,1"
  },
  {
    "nominal": "0.11"
  },
  {
    "nominal": "0.12"
  },
  {
    "nominal": "0.13"
  },
  {
    "nominal": "0.15"
  },
  {
    "nominal": "0.16"
  },
  {
    "nominal": "0.18"
  },
  {
    "nominal": "0.20"
  },
  {
    "nominal": "0.22"
  },
  {
    "nominal": "0.24"
  },
  {
    "nominal": "0.27"
  },
  {
    "nominal": "0.30"
  },
  {
    "nominal": "0.33"
  },
  {
    "nominal": "0.36"
  },
  {
    "nominal": "0.39"
  },
  {
    "nominal": "0.43"
  },
  {
    "nominal": "0.47"
  },
  {
    "nominal": "0.51"
  },
  {
    "nominal": "0.56"
  },
  {
    "nominal": "0.62"
  },
  {
    "nominal": "0.68"
  },
  {
    "nominal": "0.75"
  },
  {
    "nominal": "0.82"
  },
  {
    "nominal": "0.91"
  },
  {
    "nominal": "1.00"
  },
  {
    "nominal": "1.1"
  }
]

